xlsx2csv.py
xlsx2csv-0.8.6.dist-info/licenses/LICENSE.txt
xlsx2csv-0.8.6.dist-info/METADATA
xlsx2csv-0.8.6.dist-info/WHEEL
xlsx2csv-0.8.6.dist-info/entry_points.txt
xlsx2csv-0.8.6.dist-info/top_level.txt
xlsx2csv-0.8.6.dist-info/RECORD
